setup.py
probability_dstn/Binomialdistribution.py
probability_dstn/Gaussiandistribution.py
probability_dstn/Generaldistribution.py
probability_dstn/__init__.py
probability_dstn.egg-info/PKG-INFO
probability_dstn.egg-info/SOURCES.txt
probability_dstn.egg-info/dependency_links.txt
probability_dstn.egg-info/not-zip-safe
probability_dstn.egg-info/top_level.txt