Metadata-Version: 1.0
Name: probability-dstn
Version: 0.2
Summary: Gaussian distributions and binomial distribution
Home-page: UNKNOWN
Author: Okeowo Tunde
Author-email: okeowosamuel58.to@gmail.com
License: UNKNOWN
Platform: UNKNOWN
